<?xml version="1.0" encoding="UTF-8"?>
<metadata xml:lang="en"><Esri><CreaDate>20250219</CreaDate><CreaTime>17302600</CreaTime><ArcGISFormat>1.0</ArcGISFormat><SyncOnce>TRUE</SyncOnce><DataProperties><lineage><Process ToolSource="c:\program files (x86)\arcgis\desktop10.8\ArcToolbox\Toolboxes\Geostatistical Analyst Tools.tbx\IDW" Date="20250219" Time="173026">IDW clip PRE_2013 # C:\Users\DELL\Desktop\DSS\Varuna_Well\2013\pre\pre_2013.tif 2.25946628675398E-03 2 "NBRTYPE=Standard S_MAJOR=0.334818237933231 S_MINOR=0.334818237933231 ANGLE=0 NBR_MAX=15 NBR_MIN=10 SECTOR_TYPE=ONE_SECTOR" #</Process></lineage></DataProperties></Esri></metadata>
